.gitignore
README.md
setup.cfg
setup.py
selenium_shortcuts/__init__.py
selenium_shortcuts.egg-info/PKG-INFO
selenium_shortcuts.egg-info/SOURCES.txt
selenium_shortcuts.egg-info/dependency_links.txt
selenium_shortcuts.egg-info/requires.txt
selenium_shortcuts.egg-info/top_level.txt