Metadata-Version: 2.1
Name: selenium-shortcuts
Version: 4.3
Summary: Selenium shortcut functions
Home-page: https://github.com/xjxckk/selenium-shortcuts/
Download-URL: https://github.com/xjxckk/selenium-shortcuts/archive/refs/tags/v1.2.tar.gz
